ultrasound_rawdata_exchange/__init__.py
ultrasound_rawdata_exchange/__init__.pyi
ultrasound_rawdata_exchange/bindings.pyi
ultrasound_rawdata_exchange/bindings.pypy310-pp73-win_amd64.pyd
ultrasound_rawdata_exchange/py.typed
ultrasound_rawdata_exchange/bin/concrt140.dll
ultrasound_rawdata_exchange/bin/msvcp140.dll
ultrasound_rawdata_exchange/bin/msvcp140_1.dll
ultrasound_rawdata_exchange/bin/msvcp140_2.dll
ultrasound_rawdata_exchange/bin/msvcp140_atomic_wait.dll
ultrasound_rawdata_exchange/bin/msvcp140_codecvt_ids.dll
ultrasound_rawdata_exchange/bin/vcruntime140.dll
ultrasound_rawdata_exchange/bin/vcruntime140_1.dll
ultrasound_rawdata_exchange/include/Urx-1.3.2_static/urx/acquisition.h
ultrasound_rawdata_exchange/include/Urx-1.3.2_static/urx/config.h
ultrasound_rawdata_exchange/include/Urx-1.3.2_static/urx/dataset.h
ultrasound_rawdata_exchange/include/Urx-1.3.2_static/urx/element.h
ultrasound_rawdata_exchange/include/Urx-1.3.2_static/urx/element_geometry.h
ultrasound_rawdata_exchange/include/Urx-1.3.2_static/urx/enums.h
ultrasound_rawdata_exchange/include/Urx-1.3.2_static/urx/event.h
ultrasound_rawdata_exchange/include/Urx-1.3.2_static/urx/excitation.h
ultrasound_rawdata_exchange/include/Urx-1.3.2_static/urx/group.h
ultrasound_rawdata_exchange/include/Urx-1.3.2_static/urx/group_data.h
ultrasound_rawdata_exchange/include/Urx-1.3.2_static/urx/impulse_response.h
ultrasound_rawdata_exchange/include/Urx-1.3.2_static/urx/probe.h
ultrasound_rawdata_exchange/include/Urx-1.3.2_static/urx/receive_setup.h
ultrasound_rawdata_exchange/include/Urx-1.3.2_static/urx/transform.h
ultrasound_rawdata_exchange/include/Urx-1.3.2_static/urx/transmit_setup.h
ultrasound_rawdata_exchange/include/Urx-1.3.2_static/urx/urx.h
ultrasound_rawdata_exchange/include/Urx-1.3.2_static/urx/vector.h
ultrasound_rawdata_exchange/include/Urx-1.3.2_static/urx/version.h
ultrasound_rawdata_exchange/include/Urx-1.3.2_static/urx/wave.h
ultrasound_rawdata_exchange/include/Urx-1.3.2_static/urx/detail/compare.h
ultrasound_rawdata_exchange-1.3.2.dist-info/License.txt
ultrasound_rawdata_exchange-1.3.2.dist-info/METADATA
ultrasound_rawdata_exchange-1.3.2.dist-info/WHEEL
ultrasound_rawdata_exchange-1.3.2.dist-info/top_level.txt
ultrasound_rawdata_exchange-1.3.2.dist-info/RECORD
